whlee/__init__.py
whlee/c.py
whlee/d.py
whlee/t.py
whlee-0.0.4.dist-info/METADATA
whlee-0.0.4.dist-info/WHEEL
whlee-0.0.4.dist-info/top_level.txt
whlee-0.0.4.dist-info/RECORD
